Metadata-Version: 2.1
Name: bournix
Version: 0.0.1a0
Summary: Bournix team utils for django
Home-page: UNKNOWN
Author: Mahdi Zarrintareh
Author-email: mza2rintareh@gmail.com
License: UNKNOWN
Platform: UNKNOWN
Requires-Python: >=3.6
